flake8_multiline_containers.py
flake8_multiline_containers-0.0.19.dist-info/LICENSE
flake8_multiline_containers-0.0.19.dist-info/METADATA
flake8_multiline_containers-0.0.19.dist-info/WHEEL
flake8_multiline_containers-0.0.19.dist-info/entry_points.txt
flake8_multiline_containers-0.0.19.dist-info/top_level.txt
flake8_multiline_containers-0.0.19.dist-info/RECORD
