Metadata-Version: 2.1
Name: flake8-multiline-containers
Version: 0.0.19
Summary: Ensure a consistent format for multiline containers.
Home-page: https://github.com/jsfehler/flake8-multiline-containers
Author: Joshua Fehler
Author-email: jsfehler@gmail.com
License: MIT
Platform: UNKNOWN
Classifier: Framework :: Flake8
Classifier: Environment :: Console
Classifier: Intended Audience :: Developers
Classifier: License :: OSI Approved :: MIT License
Classifier: Programming Language :: Python
Classifier: Programming Language :: Python :: 3.6
Classifier: Programming Language :: Python :: 3.7
Classifier: Programming Language :: Python :: 3.8
Classifier: Programming Language :: Python :: 3.9
Classifier: Programming Language :: Python :: 3.10
Classifier: Topic :: Software Development :: Libraries :: Python Modules
Classifier: Topic :: Software Development :: Quality Assurance
License-File: LICENSE
Requires-Dist: flake8 (>=3.7.9)
Requires-Dist: attrs (>=19.3.0)
